<?xml version="1.0" encoding="UTF-8"?>
<Index xmlns="http://www.tso.co.uk/assets/namespace/gazetteindex" editionCode="L" page="114" pageID="https://www.thegazette.co.uk/id/London/index/year/1975/volume/4/page/114" pagePDF="https://www.thegazette.co.uk/London/index/year/1975/volume/4/page/114" pageRDF="https://www.thegazette.co.uk/London/index/year/1975/volume/4/page/114?view=linked-data" type="index" volume="4" year="1975">
  <KeyDitto>___ ___ ___ ___</KeyDitto>
  <KeyDitto>___ ___</KeyDitto>
  <KeyDitto>___ ___</KeyDitto>
  <KeyDitto>___ ___ ___</KeyDitto>
  <KeyDitto>___ ___ ___</KeyDitto>
  <KeyDitto>— ___ ___ ___</KeyDitto>
  <KeyDitto>___ -— ___</KeyDitto>
  <KeyDitto>___ ___</KeyDitto>
  <KeyDitto>___ ___</KeyDitto>
  <KeyDitto>— ___ ___ ___</KeyDitto>
  <KeyDitto>___ ___</KeyDitto>
  <KeyDitto>___ ___ ___</KeyDitto>
  <KeyDitto>___ ___ ___</KeyDitto>
  <KeyDitto>___ ___</KeyDitto>
  <KeyDitto>___ ___ ___</KeyDitto>
  <KeyDitto>___ ___ ___</KeyDitto>
  <KeyDitto>___ ___</KeyDitto>
  <KeyDitto>___ ___</KeyDitto>
  <KeyDitto>___ ___ ___ -</KeyDitto>
  <KeyDitto>___ ___ ___</KeyDitto>
  <KeyDitto>___ ___ ___</KeyDitto>
  <KeyDitto>___ — ___ ___ ___</KeyDitto>
  <KeyDitto>___ ___ ___</KeyDitto>
  <KeyDitto>___ ___</KeyDitto>
  <KeyDitto>___ ___</KeyDitto>
  <KeyDitto>___</KeyDitto>
  <KeyDitto>___ ___</KeyDitto>
  <KeyDitto>___ ___</KeyDitto>
  <KeyDitto>___ ___</KeyDitto>
  <KeyDitto>___ ___ ___</KeyDitto>
  <KeyDitto>___ ___</KeyDitto>
  <KeyDitto>___ ___ ___</KeyDitto>
  <KeyDitto>— ___ ___</KeyDitto>
  <KeyDitto>___ ___ ___</KeyDitto>
  <KeyDitto>___ — ___ ___</KeyDitto>
  <KeyDitto>___ ___ ___</KeyDitto>
  <KeyDitto>— ___ ___</KeyDitto>
  <KeyDitto>— ___ ___</KeyDitto>
  <KeyDitto>___ ___</KeyDitto>
  <KeyDitto>___ ___ ___</KeyDitto>
  <KeyDitto>___ ___ -—</KeyDitto>
  <KeyDitto>___ ___</KeyDitto>
  <KeyDitto>___ ___</KeyDitto>
</Index>

